pdpatch/__init__.py
pdpatch/_modidx.py
pdpatch/_nbdev.py
pdpatch/all.py
pdpatch/case.py
pdpatch/core.py
pdpatch/display.py
pdpatch/express.py
pdpatch/seaborn.py
pdpatch/transformer.py
pdpatch-0.1.9.dist-info/LICENSE
pdpatch-0.1.9.dist-info/METADATA
pdpatch-0.1.9.dist-info/WHEEL
pdpatch-0.1.9.dist-info/entry_points.txt
pdpatch-0.1.9.dist-info/top_level.txt
pdpatch-0.1.9.dist-info/RECORD
