Metadata-Version: 2.1
Name: pdpatch
Version: 0.1.9
Summary: New methods for pandas DataFrame and Series.
Home-page: https://github.com/asappinc/pdpatch/tree/main/
Author: Andres Babino
Author-email: ababino@asapp.com
License: MIT License
Keywords: pandas patch
Classifier: Development Status :: 3 - Alpha
Classifier: Intended Audience :: Developers
Classifier: Natural Language :: English
Classifier: Programming Language :: Python :: 3.6
Classifier: Programming Language :: Python :: 3.7
Classifier: Programming Language :: Python :: 3.8
Classifier: Programming Language :: Python :: 3.9
Classifier: Programming Language :: Python :: 3.10
Classifier: License :: OSI Approved :: MIT License
Requires-Python: >=3.6
License-File: LICENSE
Requires-Dist: pandas
Requires-Dist: fastcore
Requires-Dist: ipywidgets
Requires-Dist: IPython
Requires-Dist: pyyaml
Requires-Dist: jinja2
Requires-Dist: seaborn (>=0.11.2)
Requires-Dist: plotly
Provides-Extra: dev
Requires-Dist: nbdev (>=2.1.3) ; extra == 'dev'
Requires-Dist: kaleido ; extra == 'dev'
Requires-Dist: twine ; extra == 'dev'
Requires-Dist: statsmodels ; extra == 'dev'
Requires-Dist: scikit-image ; extra == 'dev'
Requires-Dist: notebook ; extra == 'dev'
Requires-Dist: scikit-learn ; extra == 'dev'
